booba/__init__.py
booba/src/__init__.py
booba/src/dnn.py
booba/src/nn_1hl.py
booba/utils/__init__.py
booba/utils/dnn_utils.py
booba/utils/planar_utils.py
booba/utils/process_datasets.py
booba/utils/test_utils.py
booba/utils/test_utils_nn1hl.py
build/lib/booba/__init__.py
build/lib/booba/src/__init__.py
build/lib/booba/src/dnn.py
build/lib/booba/src/nn_1hl.py
build/lib/booba/utils/__init__.py
build/lib/booba/utils/dnn_utils.py
build/lib/booba/utils/planar_utils.py
build/lib/booba/utils/process_datasets.py
build/lib/booba/utils/test_utils.py
build/lib/booba/utils/test_utils_nn1hl.py
build/lib/examples/__init__.py
build/lib/examples/dnn_test.py
build/lib/examples/snn_test.py
build/lib/tests/dnn_tests.py
build/lib/tests/public_tests.py
build/lib/tests/public_tests_nn1hl.py
build/lib/tests/shallow_nn_tests.py
build/lib/tests/snn_tests.py
build/lib/tests/testCases.py
build/lib/tests/testCases_v2_nn1hl.py
examples/__init__.py
examples/dnn_test.py
examples/snn_test.py
tests/dnn_tests.py
tests/public_tests.py
tests/public_tests_nn1hl.py
tests/shallow_nn_tests.py
tests/snn_tests.py
tests/testCases.py
tests/testCases_v2_nn1hl.py
booba_libdnn-0.0.1.dist-info/LICENSE
booba_libdnn-0.0.1.dist-info/METADATA
booba_libdnn-0.0.1.dist-info/WHEEL
booba_libdnn-0.0.1.dist-info/top_level.txt
booba_libdnn-0.0.1.dist-info/RECORD
