Metadata-Version: 2.1
Name: booba-libdnn
Version: 0.0.1
Summary: Booba is a library for building deep neural networks.
Home-page: https://github.com/amonteir/libdeeplearning
Author: angelogg
Author-email: afrmonteiro@gmail.com
License: GNU General Public License v3 (GPLv3)
Platform: UNKNOWN
Classifier: Development Status :: 3 - Alpha
Classifier: Intended Audience :: Developers
Classifier: Intended Audience :: Education
Classifier: Intended Audience :: Science/Research
Classifier: License :: OSI Approved :: GNU General Public License v3 (GPLv3)
Classifier: Programming Language :: Python :: 3
Classifier: Programming Language :: Python :: 3.6
Classifier: Programming Language :: Python :: 3.7
Classifier: Topic :: Scientific/Engineering :: Mathematics
Classifier: Topic :: Software Development :: Libraries :: Python Modules
Classifier: Topic :: Software Development :: Libraries
License-File: LICENSE
Requires-Dist: numpy (>=1.20.3)
Requires-Dist: matplotlib (>=3.4.3)
Requires-Dist: h5py (>=3.3.0)
